[
  {
    "ore": "astralsorcery:blockcustomore",
    "oremeta": 0,
    "source": "minecraft:stone",
    "srcmeta": 0,
    "veins": 6,
    "size": 8,
    "miny": 10,
    "maxy": 64
  },
  {
    "ore": "thermalfoundation:ore",
    "oremeta": 5,
    "source": "minecraft:stone",
    "srcmeta": 0,
    "veins": 48,
    "size": 8,
    "miny": 10,
    "maxy": 246
  },
  {
    "ore": "minecraft:iron_ore",
    "oremeta": 0,
    "source": "minecraft:stone",
    "srcmeta": 0,
    "veins": 64,
    "size": 8,
    "miny": 10,
    "maxy": 246
  },
  {
    "ore": "minecraft:gold_ore",
    "oremeta": 0,
    "source": "minecraft:stone",
    "srcmeta": 0,
    "veins": 32,
    "size": 8,
    "miny": 10,
    "maxy": 246
  },
  {
    "ore": "minecraft:diamond_ore",
    "oremeta": 0,
    "source": "minecraft:stone",
    "srcmeta": 0,
    "veins": 6,
    "size": 8,
    "miny": 182,
    "maxy": 246
  },
  {
    "ore": "minecraft:monster_egg",
    "oremeta": 0,
    "source": "minecraft:stone",
    "srcmeta": 0,
    "veins": 48,
    "size": 24,
    "miny": 10,
    "maxy": 246
  }
]